src/__init__.py
src/antena.py
src/test.py
c12arrayfactor-0.1.dist-info/LICENSE.txt
c12arrayfactor-0.1.dist-info/METADATA
c12arrayfactor-0.1.dist-info/WHEEL
c12arrayfactor-0.1.dist-info/top_level.txt
c12arrayfactor-0.1.dist-info/RECORD
