Metadata-Version: 2.1
Name: c12arrayfactor
Version: 0.1
Summary: fractal antenna
Home-page: UNKNOWN
Author: c12
Author-email: k.saichandana17@gmail.com
License: UNKNOWN
Platform: UNKNOWN
Classifier: Programming Language :: Python :: 3
Classifier: License :: OSI Approved :: MIT License
Classifier: Operating System :: OS Independent
License-File: LICENSE.txt
